metys/Chunk.py
metys/Formatter.py
metys/Weave.py
metys/__init__.py
metys/__main__.py
metys/Processors/ApplyDefaultOptions.py
metys/Processors/DeduceOptions.py
metys/Processors/EvaluateCode.py
metys/Processors/FormatOutput.py
metys/Processors/NameChunks.py
metys/Processors/ParseInput.py
metys/Processors/WriteOutput.py
metys/Processors/__init__.py
metys-0.1.2.dist-info/LICENSE.md
metys-0.1.2.dist-info/METADATA
metys-0.1.2.dist-info/WHEEL
metys-0.1.2.dist-info/entry_points.txt
metys-0.1.2.dist-info/top_level.txt
metys-0.1.2.dist-info/RECORD
