Metadata-Version: 2.1
Name: metys
Version: 0.1.2
Summary: Multi-kernel/Multi-session Jupyter scientific report generator and literate programming tool.
Home-page: UNKNOWN
Author: Tarn W. Burton
License: MIT
Platform: UNKNOWN
Classifier: Programming Language :: Python
Classifier: Programming Language :: Python :: 3.7
